optym/__init__.py
optym/optym.py
optym-0.0.1.dist-info/LICENSE
optym-0.0.1.dist-info/METADATA
optym-0.0.1.dist-info/WHEEL
optym-0.0.1.dist-info/top_level.txt
optym-0.0.1.dist-info/RECORD
