Metadata-Version: 2.1
Name: optym
Version: 0.0.1
Summary: Some optimization functions
Home-page: UNKNOWN
Author: Eduardo M. de Morais
Author-email: emdemor415@gmail.com
License: MIT License
Platform: UNKNOWN
Requires-Dist: numpy
Requires-Dist: pandas
Requires-Dist: setuptools
